LICENSE
MANIFEST.in
README.md
pyproject.toml
setup.cfg
setup.py
./mmpretrain/__init__.py
./mmpretrain/registry.py
./mmpretrain/version.py
./mmpretrain/.mim/dataset-index.yml
./mmpretrain/.mim/model-index.yml
./mmpretrain/.mim/configs/_base_/default_runtime.py
./mmpretrain/.mim/configs/_base_/datasets/cifar100_bs16.py
./mmpretrain/.mim/configs/_base_/datasets/cifar10_bs16.py
./mmpretrain/.mim/configs/_base_/datasets/coco_caption.py
./mmpretrain/.mim/configs/_base_/datasets/coco_okvqa.py
./mmpretrain/.mim/configs/_base_/datasets/coco_retrieval.py
./mmpretrain/.mim/configs/_base_/datasets/coco_vg_vqa.py
./mmpretrain/.mim/configs/_base_/datasets/coco_vqa.py
./mmpretrain/.mim/configs/_base_/datasets/cub_bs8_384.py
./mmpretrain/.mim/configs/_base_/datasets/cub_bs8_448.py
./mmpretrain/.mim/configs/_base_/datasets/flickr30k_caption.py
./mmpretrain/.mim/configs/_base_/datasets/flickr30k_retrieval.py
./mmpretrain/.mim/configs/_base_/datasets/gqa.py
./mmpretrain/.mim/configs/_base_/datasets/imagenet21k_bs128.py
./mmpretrain/.mim/configs/_base_/datasets/imagenet_bs128_mbv3.py
./mmpretrain/.mim/configs/_base_/datasets/imagenet_bs128_poolformer_medium_224.py
./mmpretrain/.mim/configs/_base_/datasets/imagenet_bs128_poolformer_small_224.py
./mmpretrain/.mim/configs/_base_/datasets/imagenet_bs128_revvit_224.py
./mmpretrain/.mim/configs/_base_/datasets/imagenet_bs128_riformer_medium_384.py
./mmpretrain/.mim/configs/_base_/datasets/imagenet_bs128_riformer_small_384.py
./mmpretrain/.mim/configs/_base_/datasets/imagenet_bs128_vig_224.py
./mmpretrain/.mim/configs/_base_/datasets/imagenet_bs16_eva_196.py
./mmpretrain/.mim/configs/_base_/datasets/imagenet_bs16_eva_336.py
./mmpretrain/.mim/configs/_base_/datasets/imagenet_bs16_eva_448.py
./mmpretrain/.mim/configs/_base_/datasets/imagenet_bs16_eva_560.py
./mmpretrain/.mim/configs/_base_/datasets/imagenet_bs16_pil_bicubic_384.py
./mmpretrain/.mim/configs/_base_/datasets/imagenet_bs256_beitv2.py
onedl_mmpretrain.egg-info/PKG-INFO
onedl_mmpretrain.egg-info/SOURCES.txt
onedl_mmpretrain.egg-info/dependency_links.txt
onedl_mmpretrain.egg-info/requires.txt
onedl_mmpretrain.egg-info/top_level.txt
