Metadata-Version: 2.4
Name: onedl-mmpretrain
Version: 1.3.0
Summary: OneDL Model Pretraining Toolbox and Benchmark
Author: OneDL Pretrain Contributors
Author-email: VBTI Contributors <oss-team@vbti.nl>
License-Expression: Apache-2.0
Project-URL: Homepage, https://onedl.ai
Project-URL: Repository, https://github.com/VBTI-development/onedl-mmpretrain
Project-URL: Documentation, https://onedl-mmpretrain.readthedocs.io/en/latest/
Keywords: computer vision,image classification,unsupervised learning,self-supervised learning
Classifier: Development Status :: 4 - Beta
Classifier: Operating System :: OS Independent
Classifier: Programming Language :: Python :: 3
Classifier: Programming Language :: Python :: 3.10
Classifier: Programming Language :: Python :: 3.11
Classifier: Topic :: Scientific/Engineering :: Artificial Intelligence
Requires-Python: >=3.10
License-File: LICENSE
Requires-Dist: einops
Requires-Dist: importlib-metadata
Requires-Dist: mat4py
Requires-Dist: matplotlib
Requires-Dist: modelindex
Requires-Dist: numpy
Requires-Dist: rich
Provides-Extra: multimodal
Requires-Dist: pycocotools; extra == "multimodal"
Requires-Dist: transformers>=4.53.0; extra == "multimodal"
Provides-Extra: mminstall
Requires-Dist: onedl-mmcv>=2.0.0; extra == "mminstall"
Requires-Dist: onedl-mmengine>=0.10.8rc1; extra == "mminstall"
Provides-Extra: optional
Requires-Dist: albumentations~=1.4; extra == "optional"
Requires-Dist: grad-cam<1.5.0,>=1.3.7; extra == "optional"
Requires-Dist: requests; extra == "optional"
Requires-Dist: scikit-learn>=1.5; extra == "optional"
Provides-Extra: torch
Requires-Dist: torch; extra == "torch"
Requires-Dist: torchvision; extra == "torch"
Dynamic: license-file
